docking_py/__init__.py
docking_py/cli.py
docking_py/docking.py
docking_py/tests/__init__.py
docking_py/tests/test_docking_py.py
docking_py/tests/input/1hsg.pdb
docking_py/tests/input/4yob.pdb
docking_py/tests/input/lig.pdbqt
docking_py/tests/input/rec.pdbqt
docking_py-0.3.0.dist-info/AUTHORS.rst
docking_py-0.3.0.dist-info/LICENSE
docking_py-0.3.0.dist-info/METADATA
docking_py-0.3.0.dist-info/WHEEL
docking_py-0.3.0.dist-info/entry_points.txt
docking_py-0.3.0.dist-info/top_level.txt
docking_py-0.3.0.dist-info/RECORD
