Metadata-Version: 2.1
Name: docking-py
Version: 0.3.0
Summary: Docking_py is a python library allowing a simplified use of the Smina, vina, qvina2 and qvinaw docking software. Docking_py can be easily automatize and scripted.
Home-page: https://github.com/samuelmurail/docking_py
Author: Samuel Murail
Author-email: samuel.murail@u-paris.fr
License: GNU General Public License v2 (GPLv2)
Keywords: docking_py
Platform: UNKNOWN
Classifier: Development Status :: 2 - Pre-Alpha
Classifier: Intended Audience :: Developers
Classifier: License :: OSI Approved :: GNU General Public License v2 (GPLv2)
Classifier: Natural Language :: English
Classifier: Operating System :: OS Independent
Classifier: Programming Language :: Python :: 3
Classifier: Programming Language :: Python :: 3.5
Classifier: Programming Language :: Python :: 3.6
Classifier: Programming Language :: Python :: 3.7
Classifier: Programming Language :: Python :: 3.8
Classifier: Topic :: Scientific/Engineering :: Bio-Informatics
Requires-Python: >=3.5
Requires-Dist: numpy
Requires-Dist: os-command-py
Requires-Dist: pdb-manip-py
Requires-Dist: pdb2pqr-htmd-propka30
